proteinpy/__init__.py
proteinpy/core.py
proteinpy-0.1.2.dist-info/licenses/LICENSE
proteinpy-0.1.2.dist-info/METADATA
proteinpy-0.1.2.dist-info/WHEEL
proteinpy-0.1.2.dist-info/top_level.txt
proteinpy-0.1.2.dist-info/RECORD
